{"cameraMode":{"drawMode":0,"name":"Shaded","section":"Shading Mode"},"sceneLighting":true,"audioPlay":false,"sceneViewState":{"m_AlwaysRefresh":false,"showFog":true,"showSkybox":true,"showFlares":true,"showImageEffects":true,"showParticleSystems":true,"showVisualEffectGraphs":true,"m_FxEnabled":true},"in2DMode":false,"pivot":{"x":510.5707092285156,"y":-6.1834716796875,"z":504.2730407714844},"rotation":{"x":-0.5764723420143127,"y":0.007433633785694838,"z":-0.0028406328056007625,"w":-0.8176029324531555},"size":53.031494140625,"orthographic":false}